assimp_py/assimp_py.pyi
assimp_py/assimp_py.cpython-310-powerpc64le-linux-gnu.so
assimp_py/__init__.py
assimp_py-1.1.0.dist-info/top_level.txt
assimp_py-1.1.0.dist-info/METADATA
assimp_py-1.1.0.dist-info/RECORD
assimp_py-1.1.0.dist-info/WHEEL
assimp_py-1.1.0.dist-info/licenses/LICENSE
assimp_py-1.1.0.dist-info/licenses/src/assimp/LICENSE
assimp_py.libs/libstdc++-29c3693a.so.6.0.32
assimp_py.libs/libgcc_s-18b5a48e.so.1
