Metadata-Version: 2.4
Name: assimp_py
Version: 1.1.0
Summary: Minimal Python Bindings for ASSIMP Library using C-API
Author-email: Ian Ichung'wa <karanjaichungwa@gmail.com>
Project-URL: Homepage, https://github.com/ranjian0/assimp_py
Project-URL: Repository, https://github.com/ranjian0/assimp_py
Keywords: ASSIMP,3D,Graphics
Classifier: Programming Language :: Python :: 3
Classifier: Programming Language :: Python :: 3.9
Classifier: Programming Language :: Python :: 3.10
Classifier: Programming Language :: Python :: 3.11
Classifier: Programming Language :: Python :: 3.12
Classifier: Programming Language :: Python :: 3.13
Requires-Python: >=3.9
License-File: LICENSE
License-File: src/assimp/LICENSE
Provides-Extra: test
Requires-Dist: pytest; extra == "test"
Requires-Dist: memory-profiler; extra == "test"
Dynamic: license-file
